indraa/__init__.py
indraa/main.py
indraa-2.0.dist-info/LICENSE
indraa-2.0.dist-info/METADATA
indraa-2.0.dist-info/WHEEL
indraa-2.0.dist-info/entry_points.txt
indraa-2.0.dist-info/top_level.txt
indraa-2.0.dist-info/RECORD
