Metadata-Version: 2.1
Name: indraa
Version: 2.0
Summary: Indraa is a powerful, versatile, and user-friendly Python-based network scanning and vulnerability assessment tool.
Home-page: https://github.com/R0X4R/indraa
Author: Eshan Singh
Author-email: r0x4r@yahoo.com
License: MIT
Platform: UNKNOWN
Classifier: Programming Language :: Python :: 3
Classifier: License :: OSI Approved :: MIT License
Classifier: Operating System :: OS Independent
Classifier: Intended Audience :: Developers
Classifier: Intended Audience :: Information Technology
Classifier: Topic :: Security
Classifier: Topic :: Software Development :: Libraries :: Python Modules
Requires-Python: >=3.6
License-File: LICENSE
Requires-Dist: Wappalyzer
Requires-Dist: argparse
Requires-Dist: requests
